{
  "xau": {
    "change_val": 0,
    "change_pct": 0,
    "value": 751311190,
    "date": 1769999250
  },
  "usd_xau": {
    "change_val": 0,
    "change_pct": 0,
    "value": "4734.16",
    "date": 1769999250
  },
  "bub_sekkeh": {
    "change_val": 0,
    "change_pct": 0,
    "value": 11961070,
    "date": 1769999250
  },
  "bub_bahar": {
    "change_val": 0,
    "change_pct": 0,
    "value": 8691070,
    "date": 1769999250
  },
  "bub_nim": {
    "change_val": 0,
    "change_pct": 0,
    "value": 10976400,
    "date": 1769999250
  },
  "bub_rob": {
    "change_val": 0,
    "change_pct": 0,
    "value": 9473200,
    "date": 1769999250
  },
  "bub_18ayar": {
    "change_val": 0,
    "change_pct": 0,
    "value": 467090,
    "date": 1769999250
  },
  "bub_gerami": {
    "change_val": 0,
    "change_pct": 0,
    "value": 730310,
    "date": 1769999250
  },
  "sekkeh": {
    "change_val": 0,
    "change_pct": 0,
    "value": 188800000,
    "date": 1769999250
  },
  "bahar": {
    "change_val": 0,
    "change_pct": 0,
    "value": 185500000,
    "date": 1769999250
  },
  "nim": {
    "change_val": 0,
    "change_pct": 0,
    "value": 99400000,
    "date": 1769999250
  },
  "rob": {
    "change_val": 0,
    "change_pct": 0,
    "value": 53700000,
    "date": 1769999250
  },
  "18ayar": {
    "change_val": 0,
    "change_pct": 0,
    "value": 18583500,
    "date": 1769999250
  },
  "abshodeh": {
    "change_val": 0,
    "change_pct": 0,
    "value": 80500000,
    "date": 1769999250
  },
  "gerami": {
    "change_val": 0,
    "change_pct": 0,
    "value": 22500000,
    "date": 1769999250
  },
  "bub_abshodeh": {
    "change_val": 0,
    "change_pct": 0,
    "date": 1769999250
  }
}