{
  "xau": {
    "change_val": 0,
    "change_pct": 0,
    "value": 851714550,
    "date": 1769622149
  },
  "usd_xau": {
    "change_val": 0,
    "change_pct": 0,
    "value": "5290.1525",
    "date": 1769622149
  },
  "bub_sekkeh": {
    "change_val": 0,
    "change_pct": 0,
    "value": 3532760,
    "date": 1769622149
  },
  "bub_bahar": {
    "change_val": 0,
    "change_pct": 0,
    "value": -1437240,
    "date": 1769622149
  },
  "bub_nim": {
    "change_val": 0,
    "change_pct": 0,
    "value": 4763700,
    "date": 1769622149
  },
  "bub_rob": {
    "change_val": 0,
    "change_pct": 0,
    "value": 9866850,
    "date": 1769622149
  },
  "bub_18ayar": {
    "change_val": 0,
    "change_pct": 0,
    "value": -361070,
    "date": 1769622149
  },
  "bub_gerami": {
    "change_val": 0,
    "change_pct": 0,
    "value": -2174930,
    "date": 1769622149
  },
  "sekkeh": {
    "change_val": 0,
    "change_pct": 0,
    "value": 204000000,
    "date": 1769622149
  },
  "bahar": {
    "change_val": 0,
    "change_pct": 0,
    "value": 199000000,
    "date": 1769622149
  },
  "nim": {
    "change_val": 0,
    "change_pct": 0,
    "value": 105000000,
    "date": 1769622149
  },
  "rob": {
    "change_val": 0,
    "change_pct": 0,
    "value": 60000000,
    "date": 1769622149
  },
  "18ayar": {
    "change_val": 0,
    "change_pct": 0,
    "value": 20176370,
    "date": 1769622149
  },
  "abshodeh": {
    "change_val": 0,
    "change_pct": 0,
    "value": 87400000,
    "date": 1769622149
  },
  "gerami": {
    "change_val": 0,
    "change_pct": 0,
    "value": 22500000,
    "date": 1769622149
  },
  "bub_abshodeh": {
    "change_val": 0,
    "change_pct": 0,
    "date": 1769622149
  }
}