{
  "xau": {
    "change_val": 0,
    "change_pct": 0,
    "value": 593420640,
    "date": 1767036447
  },
  "usd_xau": {
    "change_val": 0,
    "change_pct": 0,
    "value": "4331.5375",
    "date": 1767036447
  },
  "bub_sekkeh": {
    "change_val": 0,
    "change_pct": 0,
    "value": 9318050,
    "date": 1767036447
  },
  "bub_bahar": {
    "change_val": 0,
    "change_pct": 0,
    "value": 3348050,
    "date": 1767036447
  },
  "bub_nim": {
    "change_val": 0,
    "change_pct": 0,
    "value": 13652610,
    "date": 1767036447
  },
  "bub_rob": {
    "change_val": 0,
    "change_pct": 0,
    "value": 14061310,
    "date": 1767036447
  },
  "bub_18ayar": {
    "change_val": 0,
    "change_pct": 0,
    "value": 39810,
    "date": 1767036447
  },
  "bub_gerami": {
    "change_val": 0,
    "change_pct": 0,
    "value": 5098980,
    "date": 1767036447
  },
  "sekkeh": {
    "change_val": 0,
    "change_pct": 0,
    "value": 149000000,
    "date": 1767036447
  },
  "bahar": {
    "change_val": 0,
    "change_pct": 0,
    "value": 143000000,
    "date": 1767036447
  },
  "nim": {
    "change_val": 0,
    "change_pct": 0,
    "value": 83500000,
    "date": 1767036447
  },
  "rob": {
    "change_val": 0,
    "change_pct": 0,
    "value": 49000000,
    "date": 1767036447
  },
  "18ayar": {
    "change_val": 0,
    "change_pct": 0,
    "value": 14349000,
    "date": 1767036447
  },
  "abshodeh": {
    "change_val": 0,
    "change_pct": 0,
    "value": 62157000,
    "date": 1767036447
  },
  "gerami": {
    "change_val": 0,
    "change_pct": 0,
    "value": 22300000,
    "date": 1767036447
  },
  "bub_abshodeh": {
    "change_val": 0,
    "change_pct": 0,
    "date": 1767036447
  }
}