{
  "xau": {
    "change_val": 0,
    "change_pct": 0,
    "value": 794482530,
    "date": 1779751076
  },
  "usd_xau": {
    "change_val": 0,
    "change_pct": 0,
    "value": "4579.15",
    "date": 1779751076
  },
  "bub_sekkeh": {
    "change_val": 0,
    "change_pct": 0,
    "value": -2498610,
    "date": 1779751076
  },
  "bub_bahar": {
    "change_val": 0,
    "change_pct": 0,
    "value": -7968610,
    "date": 1779751076
  },
  "bub_nim": {
    "change_val": 0,
    "change_pct": 0,
    "value": 1497190,
    "date": 1779751076
  },
  "bub_rob": {
    "change_val": 0,
    "change_pct": 0,
    "value": 6233600,
    "date": 1779751076
  },
  "bub_18ayar": {
    "change_val": 0,
    "change_pct": 0,
    "value": -16170,
    "date": 1779751076
  },
  "bub_gerami": {
    "change_val": 0,
    "change_pct": 0,
    "value": 4981110,
    "date": 1779751076
  },
  "sekkeh": {
    "change_val": 0,
    "change_pct": 0,
    "value": 184500000,
    "date": 1779751076
  },
  "bahar": {
    "change_val": 0,
    "change_pct": 0,
    "value": 179000000,
    "date": 1779751076
  },
  "nim": {
    "change_val": 0,
    "change_pct": 0,
    "value": 95000000,
    "date": 1779751076
  },
  "rob": {
    "change_val": 0,
    "change_pct": 0,
    "value": 53000000,
    "date": 1779751076
  },
  "18ayar": {
    "change_val": 0,
    "change_pct": 0,
    "value": 19141230,
    "date": 1779751076
  },
  "abshodeh": {
    "change_val": 0,
    "change_pct": 0,
    "value": 82916000,
    "date": 1779751076
  },
  "gerami": {
    "change_val": 0,
    "change_pct": 0,
    "value": 28000000,
    "date": 1779751076
  },
  "bub_abshodeh": {
    "change_val": 0,
    "change_pct": 0,
    "date": 1779751076
  }
}