{
  "xau": {
    "change_val": 0,
    "change_pct": 0,
    "value": 813070410,
    "date": 1771478249
  },
  "usd_xau": {
    "change_val": 0,
    "change_pct": 0,
    "value": "4994.29",
    "date": 1771478249
  },
  "bub_sekkeh": {
    "change_val": 0,
    "change_pct": 0,
    "value": 3427030,
    "date": 1771478249
  },
  "bub_bahar": {
    "change_val": 0,
    "change_pct": 0,
    "value": -1842970,
    "date": 1771478249
  },
  "bub_nim": {
    "change_val": 0,
    "change_pct": 0,
    "value": 3810280,
    "date": 1771478249
  },
  "bub_rob": {
    "change_val": 0,
    "change_pct": 0,
    "value": 7140140,
    "date": 1771478249
  },
  "bub_18ayar": {
    "change_val": 0,
    "change_pct": 0,
    "value": -121800,
    "date": 1771478249
  },
  "bub_gerami": {
    "change_val": 0,
    "change_pct": 0,
    "value": -1056740,
    "date": 1771478249
  },
  "sekkeh": {
    "change_val": 0,
    "change_pct": 0,
    "value": 194800000,
    "date": 1771478249
  },
  "bahar": {
    "change_val": 0,
    "change_pct": 0,
    "value": 189500000,
    "date": 1771478249
  },
  "nim": {
    "change_val": 0,
    "change_pct": 0,
    "value": 99500000,
    "date": 1771478249
  },
  "rob": {
    "change_val": 0,
    "change_pct": 0,
    "value": 55000000,
    "date": 1771478249
  },
  "18ayar": {
    "change_val": 0,
    "change_pct": 0,
    "value": 19483820,
    "date": 1771478249
  },
  "abshodeh": {
    "change_val": 0,
    "change_pct": 0,
    "value": 84400000,
    "date": 1771478249
  },
  "gerami": {
    "change_val": 0,
    "change_pct": 0,
    "value": 22500000,
    "date": 1771478249
  },
  "bub_abshodeh": {
    "change_val": 0,
    "change_pct": 0,
    "date": 1771478249
  }
}