{
  "xau": {
    "change_val": 0,
    "change_pct": 0,
    "value": 582052680,
    "date": 1766404345
  },
  "usd_xau": {
    "change_val": 0,
    "change_pct": 0,
    "value": "4409.49",
    "date": 1766404345
  },
  "bub_sekkeh": {
    "change_val": 0,
    "change_pct": 0,
    "value": 6793320,
    "date": 1766404345
  },
  "bub_bahar": {
    "change_val": 0,
    "change_pct": 0,
    "value": 1423320,
    "date": 1766404345
  },
  "bub_nim": {
    "change_val": 0,
    "change_pct": 0,
    "value": 9690080,
    "date": 1766404345
  },
  "bub_rob": {
    "change_val": 0,
    "change_pct": 0,
    "value": 9930040,
    "date": 1766404345
  },
  "bub_18ayar": {
    "change_val": 0,
    "change_pct": 0,
    "value": -101600,
    "date": 1766404345
  },
  "bub_gerami": {
    "change_val": 0,
    "change_pct": 0,
    "value": 3327910,
    "date": 1766404345
  },
  "sekkeh": {
    "change_val": 0,
    "change_pct": 0,
    "value": 143800000,
    "date": 1766404345
  },
  "bahar": {
    "change_val": 0,
    "change_pct": 0,
    "value": 138400000,
    "date": 1766404345
  },
  "nim": {
    "change_val": 0,
    "change_pct": 0,
    "value": 78200000,
    "date": 1766404345
  },
  "rob": {
    "change_val": 0,
    "change_pct": 0,
    "value": 44200000,
    "date": 1766404345
  },
  "18ayar": {
    "change_val": 0,
    "change_pct": 0,
    "value": 13933470,
    "date": 1766404345
  },
  "abshodeh": {
    "change_val": 0,
    "change_pct": 0,
    "value": 60357000,
    "date": 1766404345
  },
  "gerami": {
    "change_val": 0,
    "change_pct": 0,
    "value": 20200000,
    "date": 1766404345
  },
  "bub_abshodeh": {
    "change_val": 0,
    "change_pct": 0,
    "date": 1766404345
  }
}