{
  "xau": {
    "change_val": 0,
    "change_pct": 0,
    "value": 791658330,
    "date": 1769553781
  },
  "usd_xau": {
    "change_val": 0,
    "change_pct": 0,
    "value": "5181.01",
    "date": 1769553781
  },
  "bub_sekkeh": {
    "change_val": 0,
    "change_pct": 0,
    "value": -633980,
    "date": 1769553781
  },
  "bub_bahar": {
    "change_val": 0,
    "change_pct": 0,
    "value": -8303980,
    "date": 1769553781
  },
  "bub_nim": {
    "change_val": 0,
    "change_pct": 0,
    "value": 829460,
    "date": 1769553781
  },
  "bub_rob": {
    "change_val": 0,
    "change_pct": 0,
    "value": 7899730,
    "date": 1769553781
  },
  "bub_18ayar": {
    "change_val": 0,
    "change_pct": 0,
    "value": -921330,
    "date": 1769553781
  },
  "bub_gerami": {
    "change_val": 0,
    "change_pct": 0,
    "value": -437170,
    "date": 1769553781
  },
  "sekkeh": {
    "change_val": 0,
    "change_pct": 0,
    "value": 185700000,
    "date": 1769553781
  },
  "bahar": {
    "change_val": 0,
    "change_pct": 0,
    "value": 178000000,
    "date": 1769553781
  },
  "nim": {
    "change_val": 0,
    "change_pct": 0,
    "value": 94000000,
    "date": 1769553781
  },
  "rob": {
    "change_val": 0,
    "change_pct": 0,
    "value": 54500000,
    "date": 1769553781
  },
  "18ayar": {
    "change_val": 0,
    "change_pct": 0,
    "value": 18167970,
    "date": 1769553781
  },
  "abshodeh": {
    "change_val": 0,
    "change_pct": 0,
    "value": 78700000,
    "date": 1769553781
  },
  "gerami": {
    "change_val": 0,
    "change_pct": 0,
    "value": 22500000,
    "date": 1769553781
  },
  "bub_abshodeh": {
    "change_val": 0,
    "change_pct": 0,
    "date": 1769553781
  }
}