{
  "xau": {
    "change_val": 0,
    "change_pct": 0,
    "value": 855179550,
    "date": 1772106475
  },
  "usd_xau": {
    "change_val": 0,
    "change_pct": 0,
    "value": "5173.5",
    "date": 1772106475
  },
  "bub_sekkeh": {
    "change_val": 0,
    "change_pct": 0,
    "value": -1082670,
    "date": 1772106475
  },
  "bub_bahar": {
    "change_val": 0,
    "change_pct": 0,
    "value": -4052670,
    "date": 1772106475
  },
  "bub_nim": {
    "change_val": 0,
    "change_pct": 0,
    "value": 2856040,
    "date": 1772106475
  },
  "bub_rob": {
    "change_val": 0,
    "change_pct": 0,
    "value": 6163020,
    "date": 1772106475
  },
  "bub_18ayar": {
    "change_val": 0,
    "change_pct": 0,
    "value": -541590,
    "date": 1772106475
  },
  "bub_gerami": {
    "change_val": 0,
    "change_pct": 0,
    "value": -2275190,
    "date": 1772106475
  },
  "sekkeh": {
    "change_val": 0,
    "change_pct": 0,
    "value": 200200000,
    "date": 1772106475
  },
  "bahar": {
    "change_val": 0,
    "change_pct": 0,
    "value": 197200000,
    "date": 1772106475
  },
  "nim": {
    "change_val": 0,
    "change_pct": 0,
    "value": 103500000,
    "date": 1772106475
  },
  "rob": {
    "change_val": 0,
    "change_pct": 0,
    "value": 56500000,
    "date": 1772106475
  },
  "18ayar": {
    "change_val": 0,
    "change_pct": 0,
    "value": 20079410,
    "date": 1772106475
  },
  "abshodeh": {
    "change_val": 0,
    "change_pct": 0,
    "value": 86980000,
    "date": 1772106475
  },
  "gerami": {
    "change_val": 0,
    "change_pct": 0,
    "value": 22500000,
    "date": 1772106475
  },
  "bub_abshodeh": {
    "change_val": 0,
    "change_pct": 0,
    "date": 1772106475
  }
}