{
  "xau": {
    "change_val": 0,
    "change_pct": 0,
    "value": 960279210,
    "date": 1778485966
  },
  "usd_xau": {
    "change_val": 0,
    "change_pct": 0,
    "value": "5305.41",
    "date": 1778485966
  },
  "bub_sekkeh": {
    "change_val": 0,
    "change_pct": 0,
    "value": -28016170,
    "date": 1778485966
  },
  "bub_bahar": {
    "change_val": 0,
    "change_pct": 0,
    "value": -33986170,
    "date": 1778485966
  },
  "bub_nim": {
    "change_val": 0,
    "change_pct": 0,
    "value": -11009190,
    "date": 1778485966
  },
  "bub_rob": {
    "change_val": 0,
    "change_pct": 0,
    "value": -1519600,
    "date": 1778485966
  },
  "bub_18ayar": {
    "change_val": 0,
    "change_pct": 0,
    "value": -3156660,
    "date": 1778485966
  },
  "bub_gerami": {
    "change_val": 0,
    "change_pct": 0,
    "value": 1183680,
    "date": 1778485966
  },
  "sekkeh": {
    "change_val": 0,
    "change_pct": 0,
    "value": 198000000,
    "date": 1778485966
  },
  "bahar": {
    "change_val": 0,
    "change_pct": 0,
    "value": 192000000,
    "date": 1778485966
  },
  "nim": {
    "change_val": 0,
    "change_pct": 0,
    "value": 102000000,
    "date": 1778485966
  },
  "rob": {
    "change_val": 0,
    "change_pct": 0,
    "value": 55000000,
    "date": 1778485966
  },
  "18ayar": {
    "change_val": 0,
    "change_pct": 0,
    "value": 19998610,
    "date": 1778485966
  },
  "abshodeh": {
    "change_val": 0,
    "change_pct": 0,
    "value": 86630000,
    "date": 1778485966
  },
  "gerami": {
    "change_val": 0,
    "change_pct": 0,
    "value": 29000000,
    "date": 1778485966
  },
  "bub_abshodeh": {
    "change_val": 0,
    "change_pct": 0,
    "date": 1778485966
  }
}