{
  "xau": {
    "change_val": 0,
    "change_pct": 0,
    "value": 566581150,
    "date": 1766153850
  },
  "usd_xau": {
    "change_val": 0,
    "change_pct": 0,
    "value": "4330.005",
    "date": 1766153850
  },
  "bub_sekkeh": {
    "change_val": 0,
    "change_pct": 0,
    "value": 9434290,
    "date": 1766153850
  },
  "bub_bahar": {
    "change_val": 0,
    "change_pct": 0,
    "value": 3964290,
    "date": 1766153850
  },
  "bub_nim": {
    "change_val": 0,
    "change_pct": 0,
    "value": 10910340,
    "date": 1766153850
  },
  "bub_rob": {
    "change_val": 0,
    "change_pct": 0,
    "value": 10840170,
    "date": 1766153850
  },
  "bub_18ayar": {
    "change_val": 0,
    "change_pct": 0,
    "value": 105250,
    "date": 1766153850
  },
  "bub_gerami": {
    "change_val": 0,
    "change_pct": 0,
    "value": 3775590,
    "date": 1766153850
  },
  "sekkeh": {
    "change_val": 0,
    "change_pct": 0,
    "value": 142800000,
    "date": 1766153850
  },
  "bahar": {
    "change_val": 0,
    "change_pct": 0,
    "value": 137300000,
    "date": 1766153850
  },
  "nim": {
    "change_val": 0,
    "change_pct": 0,
    "value": 77600000,
    "date": 1766153850
  },
  "rob": {
    "change_val": 0,
    "change_pct": 0,
    "value": 44200000,
    "date": 1766153850
  },
  "18ayar": {
    "change_val": 0,
    "change_pct": 0,
    "value": 13767260,
    "date": 1766153850
  },
  "abshodeh": {
    "change_val": 0,
    "change_pct": 0,
    "value": 59637000,
    "date": 1766153850
  },
  "gerami": {
    "change_val": 0,
    "change_pct": 0,
    "value": 20200000,
    "date": 1766153850
  },
  "bub_abshodeh": {
    "change_val": 0,
    "change_pct": 0,
    "date": 1766153850
  }
}