{
  "xau": {
    "change_val": 0,
    "change_pct": 0,
    "value": 667142480,
    "date": 1768290177
  },
  "usd_xau": {
    "change_val": 0,
    "change_pct": 0,
    "value": "4582.0225",
    "date": 1768290177
  },
  "bub_sekkeh": {
    "change_val": 0,
    "change_pct": 0,
    "value": 5268810,
    "date": 1768290177
  },
  "bub_bahar": {
    "change_val": 0,
    "change_pct": 0,
    "value": 798810,
    "date": 1768290177
  },
  "bub_nim": {
    "change_val": 0,
    "change_pct": 0,
    "value": 4979060,
    "date": 1768290177
  },
  "bub_rob": {
    "change_val": 0,
    "change_pct": 0,
    "value": 11424530,
    "date": 1768290177
  },
  "bub_18ayar": {
    "change_val": 0,
    "change_pct": 0,
    "value": -229700,
    "date": 1768290177
  },
  "bub_gerami": {
    "change_val": 0,
    "change_pct": 0,
    "value": 3165780,
    "date": 1768290177
  },
  "sekkeh": {
    "change_val": 0,
    "change_pct": 0,
    "value": 162300000,
    "date": 1768290177
  },
  "bahar": {
    "change_val": 0,
    "change_pct": 0,
    "value": 157800000,
    "date": 1768290177
  },
  "nim": {
    "change_val": 0,
    "change_pct": 0,
    "value": 83500000,
    "date": 1768290177
  },
  "rob": {
    "change_val": 0,
    "change_pct": 0,
    "value": 50700000,
    "date": 1768290177
  },
  "18ayar": {
    "change_val": 0,
    "change_pct": 0,
    "value": 15857150,
    "date": 1768290177
  },
  "abshodeh": {
    "change_val": 0,
    "change_pct": 0,
    "value": 68690000,
    "date": 1768290177
  },
  "gerami": {
    "change_val": 0,
    "change_pct": 0,
    "value": 22500000,
    "date": 1768290177
  },
  "bub_abshodeh": {
    "change_val": 0,
    "change_pct": 0,
    "date": 1768290177
  }
}