{
  "xau": {
    "change_val": 0,
    "change_pct": 0,
    "value": 733356540,
    "date": 1783767010
  },
  "usd_xau": {
    "change_val": 0,
    "change_pct": 0,
    "value": "4108.44",
    "date": 1783767010
  },
  "bub_sekkeh": {
    "change_val": 0,
    "change_pct": 0,
    "value": 3386400,
    "date": 1783767010
  },
  "bub_bahar": {
    "change_val": 0,
    "change_pct": 0,
    "value": -583600,
    "date": 1783767010
  },
  "bub_nim": {
    "change_val": 0,
    "change_pct": 0,
    "value": 6688810,
    "date": 1783767010
  },
  "bub_rob": {
    "change_val": 0,
    "change_pct": 0,
    "value": 9829410,
    "date": 1783767010
  },
  "bub_18ayar": {
    "change_val": 0,
    "change_pct": 0,
    "value": -178050,
    "date": 1783767010
  },
  "bub_gerami": {
    "change_val": 0,
    "change_pct": 0,
    "value": 5249840,
    "date": 1783767010
  },
  "sekkeh": {
    "change_val": 0,
    "change_pct": 0,
    "value": 176000000,
    "date": 1783767010
  },
  "bahar": {
    "change_val": 0,
    "change_pct": 0,
    "value": 172000000,
    "date": 1783767010
  },
  "nim": {
    "change_val": 0,
    "change_pct": 0,
    "value": 93000000,
    "date": 1783767010
  },
  "rob": {
    "change_val": 0,
    "change_pct": 0,
    "value": 53000000,
    "date": 1783767010
  },
  "18ayar": {
    "change_val": 0,
    "change_pct": 0,
    "value": 17505420,
    "date": 1783767010
  },
  "abshodeh": {
    "change_val": 0,
    "change_pct": 0,
    "value": 75830000,
    "date": 1783767010
  },
  "gerami": {
    "change_val": 0,
    "change_pct": 0,
    "value": 26500000,
    "date": 1783767010
  },
  "bub_abshodeh": {
    "change_val": 0,
    "change_pct": 0,
    "date": 1783767010
  }
}