{
  "xau": {
    "change_val": 0,
    "change_pct": 0,
    "value": 592884150,
    "date": 1767523045
  },
  "usd_xau": {
    "change_val": 0,
    "change_pct": 0,
    "value": "4332.365",
    "date": 1767523045
  },
  "bub_sekkeh": {
    "change_val": 0,
    "change_pct": 0,
    "value": 9944310,
    "date": 1767523045
  },
  "bub_bahar": {
    "change_val": 0,
    "change_pct": 0,
    "value": 5974310,
    "date": 1767523045
  },
  "bub_nim": {
    "change_val": 0,
    "change_pct": 0,
    "value": 12715730,
    "date": 1767523045
  },
  "bub_rob": {
    "change_val": 0,
    "change_pct": 0,
    "value": 14792870,
    "date": 1767523045
  },
  "bub_18ayar": {
    "change_val": 0,
    "change_pct": 0,
    "value": 113930,
    "date": 1767523045
  },
  "bub_gerami": {
    "change_val": 0,
    "change_pct": 0,
    "value": 4814500,
    "date": 1767523045
  },
  "sekkeh": {
    "change_val": 0,
    "change_pct": 0,
    "value": 149500000,
    "date": 1767523045
  },
  "bahar": {
    "change_val": 0,
    "change_pct": 0,
    "value": 145500000,
    "date": 1767523045
  },
  "nim": {
    "change_val": 0,
    "change_pct": 0,
    "value": 82500000,
    "date": 1767523045
  },
  "rob": {
    "change_val": 0,
    "change_pct": 0,
    "value": 49700000,
    "date": 1767523045
  },
  "18ayar": {
    "change_val": 0,
    "change_pct": 0,
    "value": 14410180,
    "date": 1767523045
  },
  "abshodeh": {
    "change_val": 0,
    "change_pct": 0,
    "value": 62422000,
    "date": 1767523045
  },
  "gerami": {
    "change_val": 0,
    "change_pct": 0,
    "value": 22000000,
    "date": 1767523045
  },
  "bub_abshodeh": {
    "change_val": 0,
    "change_pct": 0,
    "date": 1767523045
  }
}