{
  "xau": {
    "change_val": 0,
    "change_pct": 0,
    "value": 655008350,
    "date": 1767770546
  },
  "usd_xau": {
    "change_val": 0,
    "change_pct": 0,
    "value": "4452.81",
    "date": 1767770546
  },
  "bub_sekkeh": {
    "change_val": 0,
    "change_pct": 0,
    "value": 12524380,
    "date": 1767770546
  },
  "bub_bahar": {
    "change_val": 0,
    "change_pct": 0,
    "value": 6854380,
    "date": 1767770546
  },
  "bub_nim": {
    "change_val": 0,
    "change_pct": 0,
    "value": 9406670,
    "date": 1767770546
  },
  "bub_rob": {
    "change_val": 0,
    "change_pct": 0,
    "value": 15038330,
    "date": 1767770546
  },
  "bub_18ayar": {
    "change_val": 0,
    "change_pct": 0,
    "value": 173010,
    "date": 1767770546
  },
  "bub_gerami": {
    "change_val": 0,
    "change_pct": 0,
    "value": 4216890,
    "date": 1767770546
  },
  "sekkeh": {
    "change_val": 0,
    "change_pct": 0,
    "value": 166700000,
    "date": 1767770546
  },
  "bahar": {
    "change_val": 0,
    "change_pct": 0,
    "value": 161000000,
    "date": 1767770546
  },
  "nim": {
    "change_val": 0,
    "change_pct": 0,
    "value": 86500000,
    "date": 1767770546
  },
  "rob": {
    "change_val": 0,
    "change_pct": 0,
    "value": 53600000,
    "date": 1767770546
  },
  "18ayar": {
    "change_val": 0,
    "change_pct": 0,
    "value": 15967270,
    "date": 1767770546
  },
  "abshodeh": {
    "change_val": 0,
    "change_pct": 0,
    "value": 69167000,
    "date": 1767770546
  },
  "gerami": {
    "change_val": 0,
    "change_pct": 0,
    "value": 23200000,
    "date": 1767770546
  },
  "bub_abshodeh": {
    "change_val": 0,
    "change_pct": 0,
    "date": 1767770546
  }
}