{
  "xau": {
    "change_val": 0,
    "change_pct": 0,
    "value": 838936900,
    "date": 1769705254
  },
  "usd_xau": {
    "change_val": 0,
    "change_pct": 0,
    "value": "5259.7925",
    "date": 1769705254
  },
  "bub_sekkeh": {
    "change_val": 0,
    "change_pct": 0,
    "value": 1239770,
    "date": 1769705254
  },
  "bub_bahar": {
    "change_val": 0,
    "change_pct": 0,
    "value": -3430230,
    "date": 1769705254
  },
  "bub_nim": {
    "change_val": 0,
    "change_pct": 0,
    "value": 8267030,
    "date": 1769705254
  },
  "bub_rob": {
    "change_val": 0,
    "change_pct": 0,
    "value": 9618510,
    "date": 1769705254
  },
  "bub_18ayar": {
    "change_val": 0,
    "change_pct": 0,
    "value": -152240,
    "date": 1769705254
  },
  "bub_gerami": {
    "change_val": 0,
    "change_pct": 0,
    "value": -1805200,
    "date": 1769705254
  },
  "sekkeh": {
    "change_val": 0,
    "change_pct": 0,
    "value": 198700000,
    "date": 1769705254
  },
  "bahar": {
    "change_val": 0,
    "change_pct": 0,
    "value": 194000000,
    "date": 1769705254
  },
  "nim": {
    "change_val": 0,
    "change_pct": 0,
    "value": 107000000,
    "date": 1769705254
  },
  "rob": {
    "change_val": 0,
    "change_pct": 0,
    "value": 59000000,
    "date": 1769705254
  },
  "18ayar": {
    "change_val": 0,
    "change_pct": 0,
    "value": 20077100,
    "date": 1769705254
  },
  "abshodeh": {
    "change_val": 0,
    "change_pct": 0,
    "value": 86970000,
    "date": 1769705254
  },
  "gerami": {
    "change_val": 0,
    "change_pct": 0,
    "value": 22500000,
    "date": 1769705254
  },
  "bub_abshodeh": {
    "change_val": 0,
    "change_pct": 0,
    "date": 1769705254
  }
}