{
  "xau": {
    "change_val": 0,
    "change_pct": 0,
    "value": 825063510,
    "date": 1770767252
  },
  "usd_xau": {
    "change_val": 0,
    "change_pct": 0,
    "value": "5046.26",
    "date": 1770767252
  },
  "bub_sekkeh": {
    "change_val": 0,
    "change_pct": 0,
    "value": 6304650,
    "date": 1770767252
  },
  "bub_bahar": {
    "change_val": 0,
    "change_pct": 0,
    "value": 2434650,
    "date": 1770767252
  },
  "bub_nim": {
    "change_val": 0,
    "change_pct": 0,
    "value": 4899260,
    "date": 1770767252
  },
  "bub_rob": {
    "change_val": 0,
    "change_pct": 0,
    "value": 9634630,
    "date": 1770767252
  },
  "bub_18ayar": {
    "change_val": 0,
    "change_pct": 0,
    "value": 27620,
    "date": 1770767252
  },
  "bub_gerami": {
    "change_val": 0,
    "change_pct": 0,
    "value": -1403770,
    "date": 1770767252
  },
  "sekkeh": {
    "change_val": 0,
    "change_pct": 0,
    "value": 200500000,
    "date": 1770767252
  },
  "bahar": {
    "change_val": 0,
    "change_pct": 0,
    "value": 196600000,
    "date": 1770767252
  },
  "nim": {
    "change_val": 0,
    "change_pct": 0,
    "value": 102000000,
    "date": 1770767252
  },
  "rob": {
    "change_val": 0,
    "change_pct": 0,
    "value": 58200000,
    "date": 1770767252
  },
  "18ayar": {
    "change_val": 0,
    "change_pct": 0,
    "value": 19922430,
    "date": 1770767252
  },
  "abshodeh": {
    "change_val": 0,
    "change_pct": 0,
    "value": 86300000,
    "date": 1770767252
  },
  "gerami": {
    "change_val": 0,
    "change_pct": 0,
    "value": 22500000,
    "date": 1770767252
  },
  "bub_abshodeh": {
    "change_val": 0,
    "change_pct": 0,
    "date": 1770767252
  }
}